transformation_test/__init__.py
transformation_test/de.h
transformation_test/doc/dev_doc.md
transformation_test/doc/devnotes.md
transformation_test/LogSinhTransformation.cpp
transformation_test/pytrans.cpp
transformation_test/pytrans.pyx
transformation_test/R/README.md
transformation_test/R/tests/main.cpp
transformation_test/R/tests/testtrans.vcxproj
transformation_test/R/tests/testtrans.vcxproj.filters
transformation_test/R/transr/.Rbuildignore
transformation_test/R/transr/DESCRIPTION
transformation_test/R/transr/man/BoxCox.Rd
transformation_test/R/transr/man/LogSinh.Rd
transformation_test/R/transr/man/transr-package.Rd
transformation_test/R/transr/man/YeoJohnson.Rd
transformation_test/R/transr/NAMESPACE
transformation_test/R/transr/R/RcppExports.R
transformation_test/R/transr/R/zzz.R
transformation_test/R/transr/src/BoxCoxTransformation.cpp
transformation_test/R/transr/src/LogSinhTransformation.cpp
transformation_test/R/transr/src/Makevars
transformation_test/R/transr/src/rcpp_module.cpp
transformation_test/R/transr/src/RcppExports.cpp
transformation_test/R/transr/src/SCE.h
transformation_test/R/transr/src/simplex.h
transformation_test/R/transr/src/Transformation.cpp
transformation_test/R/transr/src/Transformation.h
transformation_test/R/transr/src/transr_r.sln
transformation_test/R/transr/src/transr_r.vcxproj
transformation_test/R/transr/src/transr_r.vcxproj.filters
transformation_test/R/transr/src/YeoJohnsonTransformation.cpp
transformation_test/R/transr/vignettes/getting_started.Rmd
transformation_test/R/transr/vignettes/Using_transr.Rmd
transformation_test/SCE.h
transformation_test/simplex.h
transformation_test/SinhAsinhTransformation.cpp
transformation_test/test_pytrans.py
transformation_test/Transformation.cpp
transformation_test/Transformation.h
transformation_test/YeoJohnsonTransformation.cpp
transformation_test-0.0.3.dist-info/LICENSE
transformation_test-0.0.3.dist-info/METADATA
transformation_test-0.0.3.dist-info/WHEEL
transformation_test-0.0.3.dist-info/RECORD
