Metadata-Version: 2.1
Name: transformation_test
Version: 0.0.3
Summary: Example project for demonstrating proprietary PyPI packages
License: CSIRO Open Source Software Licence Agreement (variation of the BSD / MIT License)
Author: CSIRO
Requires-Python: >=3.13,<4.0
Classifier: License :: Other/Proprietary License
Classifier: Programming Language :: Python :: 3
Classifier: Programming Language :: Python :: 3.13
Requires-Dist: cython (==3.0.11)
Requires-Dist: setuptools (>=75.6.0,<76.0.0)
